harangued.py
harangued-0.11.dist-info/METADATA
harangued-0.11.dist-info/WHEEL
harangued-0.11.dist-info/RECORD
