Metadata-Version: 2.3
Name: harangued
Version: 0.11
Summary: Update and manage other programs/system config files safely
Author-email: Roger Gammans <rgammans@gammascience.co.uk>
License: GPLv3
Classifier: Development Status :: 3 - Alpha
Classifier: License :: OSI Approved :: GNU General Public License v3 or later (GPLv3+)
Classifier: Topic :: System :: Systems Administration
Classifier: Topic :: Text Processing :: General
Requires-Python: >=3.10
